camptown/__init__.py
camptown/__main__.py
camptown/templates/index.html
camptown/templates/player.css
camptown/templates/player.js
camptown-0.3.19.dist-info/LICENSE
camptown-0.3.19.dist-info/METADATA
camptown-0.3.19.dist-info/WHEEL
camptown-0.3.19.dist-info/RECORD
