Metadata-Version: 2.3
Name: camptown
Version: 0.3.19
Summary: Semantic-HTML player engine
License: MIT
Author: fluffy
Author-email: fluffy@beesbuzz.biz
Requires-Python: >=3.11,<4.0
Classifier: License :: OSI Approved :: MIT License
Classifier: Programming Language :: Python :: 3
Classifier: Programming Language :: Python :: 3.11
Classifier: Programming Language :: Python :: 3.12
Classifier: Programming Language :: Python :: 3.13
Requires-Dist: Jinja2 (>=3.1.5,<4.0.0)
Requires-Dist: markupsafe (>=3.0.2,<4.0.0)
Requires-Dist: mistune (>=3.1.2,<4.0.0)
Requires-Dist: smartypants (>=2.0.1,<3.0.0)
Project-URL: Documentation, https://camptown.readthedocs.io
Project-URL: Repository, https://github.com/fluffy-critter/camptown
